<annotation><filename>1c01096c082a6790_7878-w500-h400-b0-p0-traditional-dining-room.jpg</filename><folder>dining</folder><source><sourceImage>The MIT-CSAIL database of objects and scenes</sourceImage><sourceAnnotation>LabelMe Webtool</sourceAnnotation></source><object><name>wallmaterial,wallpaper</name><deleted>0</deleted><verified>0</verified><parts><hasparts/><ispartof/></parts><date>16-May-2017 05:06:21</date><id>0</id><polygon><username>anonymous</username><pt><x>138</x><y>76</y></pt><pt><x>33</x><y>41</y></pt><pt><x>31</x><y>194</y></pt><pt><x>33</x><y>203</y></pt><pt><x>136</x><y>201</y></pt></polygon></object><object><name>window,large</name><deleted>0</deleted><verified>0</verified><parts><hasparts/><ispartof/></parts><date>16-May-2017 05:07:00</date><id>1</id><polygon><username>anonymous</username><pt><x>498</x><y>211</y></pt><pt><x>498</x><y>85</y></pt><pt><x>446</x><y>94</y></pt><pt><x>421</x><y>77</y></pt><pt><x>405</x><y>79</y></pt><pt><x>391</x><y>87</y></pt><pt><x>372</x><y>98</y></pt><pt><x>366</x><y>109</y></pt><pt><x>330</x><y>118</y></pt><pt><x>330</x><y>203</y></pt></polygon></object><imagesize><nrows></nrows><ncols></ncols></imagesize><object><name>lighting,chandeliers</name><deleted>0</deleted><verified>0</verified><parts><hasparts/><ispartof/></parts><date>16-May-2017 05:10:28</date><id>2</id><polygon><username>anonymous</username><pt><x>310</x><y>12</y></pt><pt><x>338</x><y>35</y></pt><pt><x>351</x><y>68</y></pt><pt><x>353</x><y>105</y></pt><pt><x>330</x><y>123</y></pt><pt><x>310</x><y>146</y></pt><pt><x>283</x><y>127</y></pt><pt><x>262</x><y>109</y></pt><pt><x>253</x><y>90</y></pt><pt><x>262</x><y>60</y></pt><pt><x>275</x><y>31</y></pt></polygon></object><object><name>floor,carpet</name><deleted>0</deleted><verified>0</verified><parts><hasparts/><ispartof/></parts><date>16-May-2017 05:12:50</date><id>3</id><polygon><username>anonymous</username><pt><x>439</x><y>271</y></pt><pt><x>497</x><y>281</y></pt><pt><x>498</x><y>399</y></pt><pt><x>307</x><y>399</y></pt></polygon></object><object><name>door,open</name><deleted>0</deleted><verified>0</verified><parts><hasparts/><ispartof/></parts><date>16-May-2017 12:14:05</date><id>4</id><polygon><username>anonymous</username><pt><x>277</x><y>37</y></pt></polygon></object><object><name>door,open</name><deleted>0</deleted><verified>0</verified><parts><hasparts/><ispartof/></parts><date>16-May-2017 12:14:24</date><id>5</id><polygon><username>anonymous</username><pt><x>273</x><y>36</y></pt></polygon></object><object><name>loft,</name><deleted>0</deleted><verified>0</verified><parts><hasparts></hasparts><ispartof></ispartof></parts><date>17-May-2017 04:54:58</date><id>6</id><polygon><username>anonymous</username><pt><x>114</x><y>245</y></pt><pt><x>121</x><y>319</y></pt><pt><x>63</x><y>304</y></pt><pt><x>71</x><y>243</y></pt></polygon></object><object><name>door,closed</name><deleted>0</deleted><verified>0</verified><parts><hasparts></hasparts><ispartof></ispartof></parts><date>17-May-2017 04:55:22</date><id>7</id><polygon><username>anonymous</username><pt><x>241</x><y>148</y></pt><pt><x>268</x><y>147</y></pt><pt><x>266</x><y>252</y></pt><pt><x>233</x><y>248</y></pt></polygon></object></annotation>