<annotation><filename>ca61dc8a0e5c12c7_8395-w500-h666-b0-p0-traditional-bathroom.jpg</filename><folder>bathroom</folder><source><sourceImage>The MIT-CSAIL database of objects and scenes</sourceImage><sourceAnnotation>LabelMe Webtool</sourceAnnotation></source><object><name>wallmaterial,wallpaper</name><deleted>0</deleted><verified>0</verified><parts><hasparts></hasparts><ispartof></ispartof></parts><date>11-May-2017 00:26:13</date><id>0</id><polygon><username>anonymous</username><pt><x>295</x><y>153</y></pt><pt><x>290</x><y>472</y></pt><pt><x>472</x><y>509</y></pt><pt><x>461</x><y>107</y></pt></polygon></object><object><name>baseboard,</name><deleted>0</deleted><verified>0</verified><parts><hasparts></hasparts><ispartof></ispartof></parts><date>11-May-2017 00:26:53</date><id>1</id><polygon><username>anonymous</username><pt><x>273</x><y>476</y></pt><pt><x>269</x><y>504</y></pt><pt><x>432</x><y>544</y></pt><pt><x>456</x><y>537</y></pt><pt><x>465</x><y>515</y></pt></polygon></object><imagesize><nrows></nrows><ncols></ncols></imagesize></annotation>